SuperAlignment/__init__.py
SuperAlignment/base.py
SuperAlignment/utils.py
SuperAlignment-0.0.2.dist-info/METADATA
SuperAlignment-0.0.2.dist-info/WHEEL
SuperAlignment-0.0.2.dist-info/top_level.txt
SuperAlignment-0.0.2.dist-info/RECORD
