Metadata-Version: 2.1
Name: SuperAlignment
Version: 0.0.2
Summary: Utils for SuperAlignment api
Author-email: dingo0927@126.com
Project-URL: homepage, http://www.deepnlp.org
Project-URL: repository, https://github.com/rockingdingo/SuperAlignment
Keywords: AGI,SuperAlignment,SuperIntelligence
Classifier: Development Status :: 3 - Alpha
Classifier: Intended Audience :: Developers
Classifier: Topic :: Software Development :: Build Tools
Classifier: License :: OSI Approved :: MIT License
Requires-Python: >=3.4
